simile/__init__.py
simile/auth_client.py
simile/client.py
simile/exceptions.py
simile/models.py
simile/resources.py
simile-0.5.4.dist-info/licenses/LICENSE
simile-0.5.4.dist-info/METADATA
simile-0.5.4.dist-info/WHEEL
simile-0.5.4.dist-info/top_level.txt
simile-0.5.4.dist-info/RECORD
