Metadata-Version: 2.4
Name: simile
Version: 0.5.4
Summary: Package for interfacing with Simile AI agents for simulation
Author-email: Simile AI <cqz@simile.ai>
License: MIT
Project-URL: Homepage, https://github.com/simile-team/simile-sdk
Keywords: api,sdk,simile,ai-agent,simulation
Classifier: Development Status :: 3 - Alpha
Classifier: Intended Audience :: Developers
Classifier: Programming Language :: Python :: 3
Classifier: Programming Language :: Python :: 3.8
Classifier: Programming Language :: Python :: 3.9
Classifier: Programming Language :: Python :: 3.10
Classifier: Programming Language :: Python :: 3.11
Classifier: Programming Language :: Python :: 3.12
Classifier: Operating System :: OS Independent
Classifier: Topic :: Software Development :: Libraries :: Python Modules
Requires-Python: >=3.8
License-File: LICENSE
Requires-Dist: httpx>=0.20.0
Requires-Dist: pydantic>=2.0.0
Requires-Dist: genagent>=0.2.3
Dynamic: license-file
